MANIFEST.in
README.md
setup.py
_cffi_build/__init__.py
_cffi_build/stb_image.h
_cffi_build/stb_image_resize.h
_cffi_build/vulkbare_build.py
vulkbare/__init__.py
vulkbare.egg-info/PKG-INFO
vulkbare.egg-info/SOURCES.txt
vulkbare.egg-info/dependency_links.txt
vulkbare.egg-info/requires.txt
vulkbare.egg-info/top_level.txt