Metadata-Version: 1.1
Name: vulkbare
Version: 1.2.0
Summary: Vulk 3D Engine C utils functions
Home-page: http://github.com/realitix/vulk-bare
Author: realitix
Author-email: realitix@gmail.com
License: Apache2
Platform: UNKNOWN
Classifier: Development Status :: 5 - Production/Stable
Classifier: Intended Audience :: Developers
Classifier: Operating System :: Android
Classifier: Operating System :: Microsoft :: Windows
Classifier: Operating System :: POSIX :: Linux
Classifier: Natural Language :: English
Classifier: Programming Language :: Python :: 3.5
Classifier: Topic :: Multimedia :: Graphics
Classifier: Topic :: Scientific/Engineering
Classifier: Topic :: Software Development :: Libraries :: Python Modules
